quimera/__init__.py
quimera/quimera.py
quimera/start.py
quimera/wifi.py
quimera-1.1.dist-info/METADATA
quimera-1.1.dist-info/WHEEL
quimera-1.1.dist-info/top_level.txt
quimera-1.1.dist-info/RECORD
